{
  "parent": "combat:recipes/root",
  "rewards": {
    "recipes": [
      "combat:life_magic_orb"
    ]
  },
  "criteria": {
    "has_gem": {
      "trigger": "minecraft:inventory_changed",
      "conditions": {
        "items": [
          {
            "items": [
              "combat:soul_gem"
            ]
          }
        ]
      }
    },
    "has_the_recipe": {
      "trigger": "minecraft:recipe_unlocked",
      "conditions": {
        "recipe": "combat:life_magic_orb"
      }
    }
  },
  "requirements": [
    [
      "has_gem",
      "has_the_recipe"
    ]
  ]
}